fedscale/__init__.py
fedscale/cloud/__init__.py
fedscale/cloud/client_manager.py
fedscale/cloud/commons.py
fedscale/cloud/config_parser.py
fedscale/cloud/fllibs.py
fedscale/cloud/resource_manager.py
fedscale/cloud/aggregation/__init__.py
fedscale/cloud/aggregation/aggregator.py
fedscale/cloud/aggregation/aggregator_mnn.py
fedscale/cloud/aggregation/aggregator_tflite.py
fedscale/cloud/aggregation/async_aggregator.py
fedscale/cloud/aggregation/optimizers.py
fedscale/cloud/channels/__init__.py
fedscale/cloud/channels/channel_context.py
fedscale/cloud/channels/job_api_pb2.py
fedscale/cloud/channels/job_api_pb2_grpc.py
fedscale/cloud/execution/__init__.py
fedscale/cloud/execution/client_base.py
fedscale/cloud/execution/data_processor.py
fedscale/cloud/execution/executor.py
fedscale/cloud/execution/optimizers.py
fedscale/cloud/execution/rl_client.py
fedscale/cloud/execution/tensorflow_client.py
fedscale/cloud/execution/torch_client.py
fedscale/cloud/internal/__init__.py
fedscale/cloud/internal/client_metadata.py
fedscale/cloud/internal/model_adapter_base.py
fedscale/cloud/internal/tensorflow_model_adapter.py
fedscale/cloud/internal/tflite_model_adapter.py
fedscale/cloud/internal/torch_model_adapter.py
fedscale/cloud/logger/__init__.py
fedscale/cloud/logger/aggregator_logging.py
fedscale/cloud/logger/dummy_logger.py
fedscale/cloud/logger/executor_logging.py
fedscale/cloud/storage/__init__.py
fedscale/dataloaders/__init__.py
fedscale/dataloaders/amazon.py
fedscale/dataloaders/decoder.py
fedscale/dataloaders/divide_data.py
fedscale/dataloaders/dqn.py
fedscale/dataloaders/femnist.py
fedscale/dataloaders/inaturalist.py
fedscale/dataloaders/nlp.py
fedscale/dataloaders/openimage.py
fedscale/dataloaders/reddit.py
fedscale/dataloaders/sparse_image_warp.py
fedscale/dataloaders/spec_augment.py
fedscale/dataloaders/speech.py
fedscale/dataloaders/stackoverflow.py
fedscale/dataloaders/transforms_stft.py
fedscale/dataloaders/transforms_wav.py
fedscale/dataloaders/utils_data.py
fedscale-1.0.dist-info/LICENSE
fedscale-1.0.dist-info/METADATA
fedscale-1.0.dist-info/WHEEL
fedscale-1.0.dist-info/top_level.txt
fedscale-1.0.dist-info/RECORD
