Metadata-Version: 2.1
Name: fedscale
Version: 1.0
Summary: FedScale: Benchmarking Model and System Performance of Federated Learning
Home-page: https://github.com/SymbioticLab/FedScale
Author: FedScale authors
Author-email: fedscale@googlegroups.com
License: UNKNOWN
Platform: UNKNOWN
